thundergbm/__init__.py
thundergbm/libthundergbm.so
thundergbm/thundergbm.py
thundergbm-0.3.17.dist-info/LICENSE
thundergbm-0.3.17.dist-info/METADATA
thundergbm-0.3.17.dist-info/WHEEL
thundergbm-0.3.17.dist-info/top_level.txt
thundergbm-0.3.17.dist-info/RECORD
