Metadata-Version: 2.1
Name: thundergbm
Version: 0.3.17
Summary: A Fast GBM Library on GPUs and CPUs
Home-page: https://github.com/zeyiwen/thundergbm
Author: Xtra Computing Group
Maintainer: thundergbm contributors
Maintainer-email: wenzy@comp.nus.edu.sg
License: Apache-2.0
Platform: UNKNOWN
Classifier: Programming Language :: Python :: 3
Classifier: License :: OSI Approved :: Apache Software License
License-File: LICENSE
Requires-Dist: numpy
Requires-Dist: scikit-learn
Requires-Dist: scipy
